shotgrid_orm/__init__.py
shotgrid_orm/classes.py
shotgrid_orm/sgtypes.py
shotgrid_orm-0.1.1.dist-info/licenses/LICENSE
shotgrid_orm-0.1.1.dist-info/METADATA
shotgrid_orm-0.1.1.dist-info/WHEEL
shotgrid_orm-0.1.1.dist-info/top_level.txt
shotgrid_orm-0.1.1.dist-info/RECORD
