Metadata-Version: 2.4
Name: shotgrid_orm
Version: 0.1.1
Summary: Shotgrid SQLAlchemy ORM Generator - creates Python classes from a schema.
Author-email: John Em Tran <johnemtran@gmail.com>
License: This is the MIT license: http://www.opensource.org/licenses/mit-license.php
Project-URL: Homepage, https://github.com/johnetran/shotgrid_orm
Project-URL: Bug Tracker, https://github.com/johnetran/shotgrid_orm/issues
Project-URL: Repository, https://github.com/johnetran/shotgrid_orm
Keywords: shotgrid,shotgun,autodesk,orm,sqlalchemy,flow-production-tracking
Classifier: Development Status :: 4 - Beta
Classifier: Intended Audience :: Developers
Classifier: Topic :: Database
Classifier: Topic :: Software Development :: Code Generators
Classifier: Programming Language :: Python :: 3
Classifier: Programming Language :: Python :: 3.8
Classifier: Programming Language :: Python :: 3.9
Classifier: Programming Language :: Python :: 3.10
Classifier: Programming Language :: Python :: 3.11
Classifier: Programming Language :: Python :: 3.12
Classifier: Programming Language :: Python :: 3.13
Classifier: Operating System :: OS Independent
Requires-Python: >=3.8
License-File: LICENSE
Requires-Dist: shotgun-api3>=3.4.0
Requires-Dist: sqlacodegen-v2>=0.1.4
Requires-Dist: SQLAlchemy>=2.0.22
Requires-Dist: alembic>=1.12.1
Provides-Extra: dev
Requires-Dist: pytest>=7.4.0; extra == "dev"
Requires-Dist: pytest-cov>=4.1.0; extra == "dev"
Requires-Dist: black; extra == "dev"
Requires-Dist: ruff; extra == "dev"
Requires-Dist: mypy; extra == "dev"
Requires-Dist: build; extra == "dev"
Requires-Dist: twine; extra == "dev"
Requires-Dist: pre-commit; extra == "dev"
Requires-Dist: bandit[toml]; extra == "dev"
Dynamic: license-file
